odoo8_addon_product_dimension-8.0.2.0.1-py2.7-nspkg.pth
odoo8_addon_product_dimension-8.0.2.0.1.dist-info/DESCRIPTION.rst
odoo8_addon_product_dimension-8.0.2.0.1.dist-info/METADATA
odoo8_addon_product_dimension-8.0.2.0.1.dist-info/RECORD
odoo8_addon_product_dimension-8.0.2.0.1.dist-info/WHEEL
odoo8_addon_product_dimension-8.0.2.0.1.dist-info/metadata.json
odoo8_addon_product_dimension-8.0.2.0.1.dist-info/namespace_packages.txt
odoo8_addon_product_dimension-8.0.2.0.1.dist-info/top_level.txt
odoo_addons/product_dimension/README.rst
odoo_addons/product_dimension/__init__.py
odoo_addons/product_dimension/__openerp__.py
odoo_addons/product_dimension/product.py
odoo_addons/product_dimension/product_view.xml
odoo_addons/product_dimension/i18n/ca.po
odoo_addons/product_dimension/i18n/de.po
odoo_addons/product_dimension/i18n/es.po
odoo_addons/product_dimension/i18n/fr.po
odoo_addons/product_dimension/i18n/sl.po
odoo_addons/product_dimension/static/description/icon.png
odoo_addons/product_dimension/tests/__init__.py
odoo_addons/product_dimension/tests/test_compute_volume.py
